archive_retriever/__init__.py
archive_retriever/archive_retriever.py
archive_retriever/edges/__init__.py
archive_retriever/edges/after_relevance_grader_conditional_edges.py
archive_retriever/graph.py
archive_retriever/nodes/__init__.py
archive_retriever/nodes/story_relevance_grader_node.py
archive_retriever/nodes/story_retrieval_cleaner_node.py
archive_retriever/nodes/story_retrieval_planner_node.py
archive_retriever/nodes/story_retriever_node.py
archive_retriever/nodes/sub_topic_retrieval_planner_node.py
archive_retriever/nodes/topic_relevance_grader_node.py
archive_retriever/nodes/topic_retrieval_cleaner_node.py
archive_retriever/nodes/topic_retrieval_planner_node.py
archive_retriever/nodes/topic_retriever_node.py
archive_retriever/quality_config.py
archive_retriever/state/__init__.py
archive_retriever/state/agent_state.py
archive_retriever/state/article.py
archive_retriever/state/article_state.py
archive_retriever/state/story.py
archive_retriever/state/story_state.py
archive_retriever/state/topic.py
archive_retriever/state/topic_state.py
archive_retriever/utilities/__init__.py
archive_retriever/utilities/config.py
archive_retriever/utilities/generate_qdrant_date_filter.py
archive_retriever/utilities/get_article_text.py
archive_retriever-0.1.0.dist-info/METADATA
archive_retriever-0.1.0.dist-info/WHEEL
archive_retriever-0.1.0.dist-info/RECORD
