Metadata-Version: 2.1
Name: archive-retriever
Version: 0.1.0
Summary: 
Author: Your Name
Author-email: you@example.com
Requires-Python: >=3.12,<4.0
Classifier: Programming Language :: Python :: 3
Classifier: Programming Language :: Python :: 3.12
Requires-Dist: langchain-anthropic (>=0.1.20,<0.2.0)
Requires-Dist: langchain-cohere (>=0.1.9,<0.2.0)
Requires-Dist: langchain-core (>=0.2.21,<0.3.0)
Requires-Dist: langchain-openai (>=0.1.17,<0.2.0)
Requires-Dist: langchain-qdrant (>=0.1.2,<0.2.0)
Requires-Dist: langgraph (>=0.1.8,<0.2.0)
Requires-Dist: pandas (>=2.2.2,<3.0.0)
Requires-Dist: pydantic-settings (>=2.3.4,<3.0.0)
Requires-Dist: python-dotenv (>=1.0.1,<2.0.0)
Requires-Dist: streamlit (>=1.36.0,<2.0.0)
